beer_keeper/__init__.py
beer_keeper/beer.py
beer_keeper/cli.py
beer_keeper/client.py
beer_keeper/custom_exceptions.py
beer_keeper/custom_http_client.py
beer_keeper/params.py
beer_keeper-1.1.0.dist-info/entry_points.txt
beer_keeper-1.1.0.dist-info/WHEEL
beer_keeper-1.1.0.dist-info/METADATA
beer_keeper-1.1.0.dist-info/RECORD
