Metadata-Version: 2.1
Name: beer-keeper
Version: 1.1.0
Summary: 
Author: Vlad David
Author-email: vlad.david@complyadvantage.com
Requires-Python: >=3.8,<4.0
Classifier: Programming Language :: Python :: 3
Classifier: Programming Language :: Python :: 3.8
Requires-Dist: httpx (>=0.13.3,<0.14.0)
Requires-Dist: pydocstyle (>=5.0.2,<6.0.0)
Requires-Dist: requests (>=2.24.0,<3.0.0)
Requires-Dist: sphinx-automodapi (>=0.12,<0.13)
